passbolt/__init__.py
py_passbolt-0.0.19.dist-info/METADATA
py_passbolt-0.0.19.dist-info/WHEEL
py_passbolt-0.0.19.dist-info/top_level.txt
py_passbolt-0.0.19.dist-info/RECORD
